[{"text": "welcome to how to build the future today", "start": 0.03, "duration": 4.499}, {"text": "our guest is Mark Zuckerberg mark you've", "start": 1.979, "duration": 3.691}, {"text": "built one of the most influential", "start": 4.529, "duration": 2.73}, {"text": "companies in the history of the world so", "start": 5.67, "duration": 3.09}, {"text": "we are especially excited that you are", "start": 7.259, "duration": 3.081}, {"text": "here I'm not sure where to go from there", "start": 8.76, "duration": 4.35}, {"text": "um well why don't we start with just the", "start": 10.34, "duration": 5.23}, {"text": "early days of Facebook tell us what it", "start": 13.11, "duration": 6.63}, {"text": "was like when you started it sure so for", "start": 15.57, "duration": 6.09}, {"text": "me the thing that I was really", "start": 19.74, "duration": 4.82}, {"text": "fascinated by and it always have been is", "start": 21.66, "duration": 6.959}, {"text": "people right and how people work in", "start": 24.56, "duration": 5.83}, {"text": "artists in college I studied psychology", "start": 28.619, "duration": 4.62}, {"text": "and computer science and you know one of", "start": 30.39, "duration": 4.079}, {"text": "the things that you learn when you study", "start": 33.239, "duration": 3.361}, {"text": "psychology is that there are all these", "start": 34.469, "duration": 5.43}, {"text": "parts of the brain which are geared just", "start": 36.6, "duration": 6.45}, {"text": "towards understanding people right", "start": 39.899, "duration": 4.531}, {"text": "understanding language how to", "start": 43.05, "duration": 2.36}, {"text": "communicate with each other", "start": 44.43, "duration": 2.969}, {"text": "understanding facial expressions", "start": 45.41, "duration": 5.86}, {"text": "emotions processing yet when I looked", "start": 47.399, "duration": 6.18}, {"text": "out at the internet right in 2004 which", "start": 51.27, "duration": 4.289}, {"text": "is when I was getting started you can", "start": 53.579, "duration": 3.151}, {"text": "find almost anything else that you", "start": 55.559, "duration": 3.781}, {"text": "wanted right you could find news movies", "start": 56.73, "duration": 6.3}, {"text": "music reference materials but the thing", "start": 59.34, "duration": 6.389}, {"text": "that mattered the most to people which", "start": 63.03, "duration": 4.409}, {"text": "was other people and like understanding", "start": 65.729, "duration": 3.241}, {"text": "what's going on with them it just wasn't", "start": 67.439, "duration": 3.781}, {"text": "there right and I think what was going", "start": 68.97, "duration": 4.35}, {"text": "on was that all that other content was", "start": 71.22, "duration": 4.59}, {"text": "just out there able to be indexed by you", "start": 73.32, "duration": 3.96}, {"text": "know search engines and and other", "start": 75.81, "duration": 3.66}, {"text": "services but in order to understand", "start": 77.28, "duration": 3.54}, {"text": "what's going on with people you needed", "start": 79.47, "duration": 4.079}, {"text": "to build tools that made it so that they", "start": 80.82, "duration": 4.83}, {"text": "could express what was going on with", "start": 83.549, "duration": 3.57}, {"text": "themselves you know I wanted to figure", "start": 85.65, "duration": 3.329}, {"text": "out what courses to take so I I built", "start": 87.119, "duration": 5.731}, {"text": "this little website coursematch that you", "start": 88.979, "duration": 5.191}, {"text": "know that just made it so you could", "start": 92.85, "duration": 2.729}, {"text": "enter what courses you were taking and", "start": 94.17, "duration": 2.55}, {"text": "you could click on them and see who else", "start": 95.579, "duration": 3.031}, {"text": "was in them and it did all these", "start": 96.72, "duration": 3.57}, {"text": "correlations who told you people who", "start": 98.61, "duration": 4.049}, {"text": "took this course we're likely to enjoy", "start": 100.29, "duration": 4.92}, {"text": "this course too and you know the thing", "start": 102.659, "duration": 3.841}, {"text": "that just struck me from the beginning", "start": 105.21, "duration": 3.51}, {"text": "is you know people would just spend", "start": 106.5, "duration": 4.56}, {"text": "hours clicking through the here are the", "start": 108.72, "duration": 4.109}, {"text": "courses that people are taking and Wow", "start": 111.06, "duration": 3.599}, {"text": "like isn't it interesting that this", "start": 112.829, "duration": 3.451}, {"text": "person is interested in these things and", "start": 114.659, "duration": 3.39}, {"text": "it was just text right there's nothing", "start": 116.28, "duration": 3.15}, {"text": "that was like super interesting there", "start": 118.049, "duration": 3.691}, {"text": "but that just struck me is you know", "start": 119.43, "duration": 3.84}, {"text": "people have this deep thirst to", "start": 121.74, "duration": 3.059}, {"text": "understand what's going on with with", "start": 123.27, "duration": 3.989}, {"text": "those around them and you know there", "start": 124.799, "duration": 4.501}, {"text": "were probably you know 10 other things", "start": 127.259, "duration": 3.48}, {"text": "like that then I built when I was at", "start": 129.3, "duration": 4.05}, {"text": "Harvard before I actually got around to", "start": 130.739, "duration": 4.441}, {"text": "building the first version of Facebook", "start": 133.35, "duration": 3.3}, {"text": "that kind of added a lot of these things", "start": 135.18, "duration": 3.45}, {"text": "together did you think Facebook was", "start": 136.65, "duration": 3.3}, {"text": "going to be a company when you started I", "start": 138.63, "duration": 2.91}, {"text": "built the first version of Facebook", "start": 139.95, "duration": 4.5}, {"text": "because it's something that my friends", "start": 141.54, "duration": 5.34}, {"text": "and I wanted to use at Harvard a", "start": 144.45, "duration": 4.47}, {"text": "directory and a way to connect with the", "start": 146.88, "duration": 4.86}, {"text": "other people around us and I didn't", "start": 148.92, "duration": 3.75}, {"text": "think at all that was going to be a", "start": 151.74, "duration": 3.69}, {"text": "company I remember very specifically the", "start": 152.67, "duration": 6.06}, {"text": "night that that we launched the first", "start": 155.43, "duration": 6.6}, {"text": "version I went out to to get pizza with", "start": 158.73, "duration": 7.71}, {"text": "a couple of my friends who now work here", "start": 162.03, "duration": 7.86}, {"text": "and you know and I remember really", "start": 166.44, "duration": 4.77}, {"text": "clearly we were talking about how one", "start": 169.89, "duration": 3.45}, {"text": "day we thought that someone was going to", "start": 171.21, "duration": 3.87}, {"text": "build a community like this for the", "start": 173.34, "duration": 4.11}, {"text": "world and that that would be some", "start": 175.08, "duration": 5.13}, {"text": "company but like it clearly wasn't gonna", "start": 177.45, "duration": 4.92}, {"text": "be us I mean it just it wasn't even I", "start": 180.21, "duration": 4.26}, {"text": "didn't even occur yeah no I mean it", "start": 182.37, "duration": 4.2}, {"text": "wasn't even an option that we considered", "start": 184.47, "duration": 3.57}, {"text": "that it might be us I mean we just", "start": 186.57, "duration": 3.33}, {"text": "weren't focused on building a company", "start": 188.04, "duration": 3.48}, {"text": "back then we were just building", "start": 189.9, "duration": 3.33}, {"text": "something that that that we thought", "start": 191.52, "duration": 4.89}, {"text": "would be useful at our school so as you", "start": 193.23, "duration": 4.86}, {"text": "look back is there something that made", "start": 196.41, "duration": 2.97}, {"text": "Facebook different from the other", "start": 198.09, "duration": 3.54}, {"text": "projects that you had built that allowed", "start": 199.38, "duration": 4.85}, {"text": "it to turn into this the companies today", "start": 201.63, "duration": 7.38}, {"text": "um well for one I think we we kept going", "start": 204.23, "duration": 7.93}, {"text": "right so I mean they the others I mean", "start": 209.01, "duration": 6.0}, {"text": "course match and you know just the the", "start": 212.16, "duration": 5.7}, {"text": "other different crowdsource tools you", "start": 215.01, "duration": 4.05}, {"text": "know they kind of served their purpose", "start": 217.86, "duration": 3.03}, {"text": "yeah and then we were done worse", "start": 219.06, "duration": 4.26}, {"text": "with Facebook there was just such you", "start": 220.89, "duration": 4.74}, {"text": "know people loved it right and had such", "start": 223.32, "duration": 3.87}, {"text": "an intensity of using I think within a", "start": 225.63, "duration": 4.71}, {"text": "couple of weeks two-thirds of students", "start": 227.19, "duration": 5.07}, {"text": "at Harvard were using it and all these", "start": 230.34, "duration": 4.7}, {"text": "other students said MIT and other local", "start": 232.26, "duration": 5.67}, {"text": "universities were writing in asking us", "start": 235.04, "duration": 5.11}, {"text": "if we could open up Facebook it at their", "start": 237.93, "duration": 3.48}, {"text": "school so we kind of just followed that", "start": 240.15, "duration": 3.09}, {"text": "right um you know again we didn't I", "start": 241.41, "duration": 3.39}, {"text": "didn't set out and you know my roommates", "start": 243.24, "duration": 3.87}, {"text": "didn't set out to to build a service", "start": 244.8, "duration": 3.63}, {"text": "that we're going to turn into a company", "start": 247.11, "duration": 2.82}, {"text": "but we just kind of followed what people", "start": 248.43, "duration": 3.63}, {"text": "wanted and that led us to expand it to", "start": 249.93, "duration": 4.5}, {"text": "all these other schools and and", "start": 252.06, "duration": 4.83}, {"text": "eventually beyond schools and to you", "start": 254.43, "duration": 4.32}, {"text": "know at some point once we'd hired a", "start": 256.89, "duration": 3.21}, {"text": "bunch of people we decided to turn it", "start": 258.75, "duration": 3.96}, {"text": "into a company and and go for this", "start": 260.1, "duration": 4.29}, {"text": "mission of connecting the world but", "start": 262.71, "duration": 3.179}, {"text": "that's not where we started is you", "start": 264.39, "duration": 3.959}, {"text": "think about where you did start is there", "start": 265.889, "duration": 4.201}, {"text": "other advice that comes to mind that you", "start": 268.349, "duration": 4.111}, {"text": "give to other people that want to build", "start": 270.09, "duration": 4.71}, {"text": "products uh that you can take away from", "start": 272.46, "duration": 6.0}, {"text": "the early days of Facebook yeah you know", "start": 274.8, "duration": 5.22}, {"text": "I always think that you should start", "start": 278.46, "duration": 3.87}, {"text": "with the problem that you're trying to", "start": 280.02, "duration": 5.0}, {"text": "solve in the world and not start with", "start": 282.33, "duration": 4.23}, {"text": "deciding that you want to build a", "start": 285.02, "duration": 3.369}, {"text": "company writing the best company is that", "start": 286.56, "duration": 3.75}, {"text": "that get built are things that are", "start": 288.389, "duration": 4.14}, {"text": "trying to drive some kind of social", "start": 290.31, "duration": 4.199}, {"text": "change even if it's just local in one", "start": 292.529, "duration": 4.95}, {"text": "place I you know more than starting out", "start": 294.509, "duration": 4.141}, {"text": "because you want to make a bunch of", "start": 297.479, "duration": 3.21}, {"text": "money or have a lot of people working", "start": 298.65, "duration": 4.169}, {"text": "for you or or build some company in some", "start": 300.689, "duration": 3.931}, {"text": "way so you know I always think that this", "start": 302.819, "duration": 3.541}, {"text": "is kind of a perverse thing about", "start": 304.62, "duration": 3.569}, {"text": "Silicon Valley in a way through which is", "start": 306.36, "duration": 4.23}, {"text": "that you know people decide often that", "start": 308.189, "duration": 3.931}, {"text": "they want to start a company before they", "start": 310.59, "duration": 2.759}, {"text": "even decide what they want to do and", "start": 312.12, "duration": 4.109}, {"text": "that just feels really backwards to me", "start": 313.349, "duration": 4.38}, {"text": "and you know for anyone who said the", "start": 316.229, "duration": 2.46}, {"text": "experience of actually building a", "start": 317.729, "duration": 2.37}, {"text": "company you know that you go through", "start": 318.689, "duration": 2.85}, {"text": "some really hard things along the way", "start": 320.099, "duration": 3.72}, {"text": "and I think part of what gets you", "start": 321.539, "duration": 4.44}, {"text": "through that is believing in what you're", "start": 323.819, "duration": 5.07}, {"text": "doing and knowing that what you're doing", "start": 325.979, "duration": 5.49}, {"text": "is is really delivering a lot of value", "start": 328.889, "duration": 5.58}, {"text": "for people and that's I think how the", "start": 331.469, "duration": 4.73}, {"text": "best companies end up getting made I", "start": 334.469, "duration": 3.69}, {"text": "want to talk for a second about low", "start": 336.199, "duration": 3.881}, {"text": "points because I think people never", "start": 338.159, "duration": 4.111}, {"text": "appreciate how bad they really are and I", "start": 340.08, "duration": 3.299}, {"text": "think it's always reassuring to hear", "start": 342.27, "duration": 2.759}, {"text": "that even Mark Zuckerberg went through", "start": 343.379, "duration": 3.21}, {"text": "some serious low points and came out", "start": 345.029, "duration": 2.94}, {"text": "okay so can you tell us about some of", "start": 346.589, "duration": 2.85}, {"text": "the hardest parts in the history of the", "start": 347.969, "duration": 4.591}, {"text": "early history of Facebook yeah I think", "start": 349.439, "duration": 9.66}, {"text": "one of the hardest parts for me was was", "start": 352.56, "duration": 10.169}, {"text": "actually when Yahoo offered to buy the", "start": 359.099, "duration": 5.581}, {"text": "company for for a lot of money because", "start": 362.729, "duration": 3.541}, {"text": "up until that point that was this", "start": 364.68, "duration": 3.469}, {"text": "turning point in the company where", "start": 366.27, "duration": 5.91}, {"text": "before that we every day we just come in", "start": 368.149, "duration": 5.95}, {"text": "and kind of do what we thought was the", "start": 372.18, "duration": 3.599}, {"text": "right next thing to do right we'd open", "start": 374.099, "duration": 3.78}, {"text": "two more schools we we open to high", "start": 375.779, "duration": 5.341}, {"text": "school and open beyond schools and you", "start": 377.879, "duration": 5.491}, {"text": "know launch more photos so because", "start": 381.12, "duration": 4.019}, {"text": "because that's what it seemed like the", "start": 383.37, "duration": 3.15}, {"text": "next thing that we needed to do to help", "start": 385.139, "duration": 3.24}, {"text": "people express themselves and understand", "start": 386.52, "duration": 4.019}, {"text": "more what was going on around them but", "start": 388.379, "duration": 5.64}, {"text": "then no yahoo came in with this with", "start": 390.539, "duration": 4.98}, {"text": "this really meaningful offer right even", "start": 394.019, "duration": 4.281}, {"text": "a billion dollars for", "start": 395.519, "duration": 4.791}, {"text": "into the company I was a couple of years", "start": 398.3, "duration": 4.47}, {"text": "Edeka right and you know we have 10", "start": 400.31, "duration": 3.72}, {"text": "million people using the product at the", "start": 402.77, "duration": 4.56}, {"text": "time quite so it wasn't like it wasn't", "start": 404.03, "duration": 4.89}, {"text": "as if it were obvious that we were going", "start": 407.33, "duration": 4.26}, {"text": "to succeed far beyond that and that was", "start": 408.92, "duration": 5.06}, {"text": "the first point where we really had to", "start": 411.59, "duration": 5.73}, {"text": "to look at the future and say wow is", "start": 413.98, "duration": 5.59}, {"text": "what we're going to build I'm going to", "start": 417.32, "duration": 6.45}, {"text": "actually be so much more meaningful for", "start": 419.57, "duration": 5.7}, {"text": "this and you know that caused a lot of", "start": 423.77, "duration": 3.15}, {"text": "interesting conversations in the company", "start": 425.27, "duration": 3.99}, {"text": "and with our investors and you know at", "start": 426.92, "duration": 3.66}, {"text": "the end of that Dustin and I just", "start": 429.26, "duration": 3.42}, {"text": "decided you know we think that we can", "start": 430.58, "duration": 3.93}, {"text": "actually go connect more than just the", "start": 432.68, "duration": 3.54}, {"text": "10 million people who are in schools we", "start": 434.51, "duration": 3.75}, {"text": "can go beyond that and have this really", "start": 436.22, "duration": 3.78}, {"text": "be a successful thing and we decide to", "start": 438.26, "duration": 2.67}, {"text": "go for it but it was really stressful", "start": 440.0, "duration": 2.25}, {"text": "because a lot of people really thought", "start": 440.93, "duration": 3.63}, {"text": "that we should sell the company and and", "start": 442.25, "duration": 4.74}, {"text": "you know for a lot of folks who joined a", "start": 444.56, "duration": 4.11}, {"text": "start-up I feel like at that point I", "start": 446.99, "duration": 3.21}, {"text": "hadn't been very good about", "start": 448.67, "duration": 4.11}, {"text": "communicating that we were trying to go", "start": 450.2, "duration": 4.41}, {"text": "for this mission yeah you know we just", "start": 452.78, "duration": 3.42}, {"text": "showed up every day and yeah and just", "start": 454.61, "duration": 3.09}, {"text": "kind of did what we thought was the the", "start": 456.2, "duration": 3.63}, {"text": "right next thing to do so for a lot of", "start": 457.7, "duration": 3.9}, {"text": "the folks who joined early on that there", "start": 459.83, "duration": 3.48}, {"text": "weren't really aligned with me right for", "start": 461.6, "duration": 4.89}, {"text": "them you know they joined and um you", "start": 463.31, "duration": 4.83}, {"text": "know being able to sell a company for a", "start": 466.49, "duration": 3.96}, {"text": "billion dollars after a couple years was", "start": 468.14, "duration": 4.41}, {"text": "I was like a home run right and it is a", "start": 470.45, "duration": 3.72}, {"text": "home run right then and that's you know", "start": 472.55, "duration": 4.8}, {"text": "I think that that's um I get that but", "start": 474.17, "duration": 5.43}, {"text": "you know that I think that the fact that", "start": 477.35, "duration": 3.84}, {"text": "I didn't communicate very well about", "start": 479.6, "duration": 4.17}, {"text": "what we were trying to do cause caused", "start": 481.19, "duration": 4.2}, {"text": "this huge tension and the part that was", "start": 483.77, "duration": 3.21}, {"text": "painful wasn't wasn't turning down the", "start": 485.39, "duration": 3.8}, {"text": "offer it was the fact that after that a", "start": 486.98, "duration": 4.35}, {"text": "huge amounts of the company quit because", "start": 489.19, "duration": 3.61}, {"text": "they didn't believe in and what we were", "start": 491.33, "duration": 3.0}, {"text": "what we were doing right I mean if you", "start": 492.8, "duration": 3.21}, {"text": "look at the management team that we had", "start": 494.33, "duration": 3.39}, {"text": "did that fellow management team leave", "start": 496.01, "duration": 3.48}, {"text": "the whole management team was gone", "start": 497.72, "duration": 4.74}, {"text": "within within about a year after that", "start": 499.49, "duration": 5.01}, {"text": "did you ever regret that decision in", "start": 502.46, "duration": 3.81}, {"text": "that period like where there are times", "start": 504.5, "duration": 2.91}, {"text": "where you were like well we should have", "start": 506.27, "duration": 3.6}, {"text": "sold um you know we were I was I got", "start": 507.41, "duration": 4.77}, {"text": "really lucky because you know not only", "start": 509.87, "duration": 4.71}, {"text": "did did what I believed in end up", "start": 512.18, "duration": 4.02}, {"text": "working out but it ended up working out", "start": 514.58, "duration": 3.81}, {"text": "pretty quickly right so it literally you", "start": 516.2, "duration": 3.24}, {"text": "know I think this was in the summer of", "start": 518.39, "duration": 7.14}, {"text": "2006 and by I think the next month after", "start": 519.44, "duration": 7.62}, {"text": "that we launched news feed or which now", "start": 525.53, "duration": 2.88}, {"text": "ten years later looking back at it is", "start": 527.06, "duration": 2.88}, {"text": "you know one of the", "start": 528.41, "duration": 4.23}, {"text": "most used products in the world and then", "start": 529.94, "duration": 4.98}, {"text": "we launched the ability for anyone to", "start": 532.64, "duration": 4.38}, {"text": "sign up which immediately started", "start": 534.92, "duration": 5.43}, {"text": "growing the community so within a few", "start": 537.02, "duration": 4.77}, {"text": "months after turning down the offer I", "start": 540.35, "duration": 2.64}, {"text": "think it was actually pretty clear that", "start": 541.79, "duration": 4.14}, {"text": "that was the right decision but you know", "start": 542.99, "duration": 4.32}, {"text": "I think you know since then there have", "start": 545.93, "duration": 2.43}, {"text": "been much harder decisions that we've", "start": 547.31, "duration": 2.46}, {"text": "had to make where you know sometimes you", "start": 548.36, "duration": 2.82}, {"text": "have to you have to bet on something and", "start": 549.77, "duration": 3.12}, {"text": "and you know either", "start": 551.18, "duration": 3.45}, {"text": "you know bet the direction of the", "start": 552.89, "duration": 3.99}, {"text": "company or you know bet billions of", "start": 554.63, "duration": 3.81}, {"text": "dollars on something it's not going to", "start": 556.88, "duration": 2.97}, {"text": "be clear with your right for five or ten", "start": 558.44, "duration": 3.51}, {"text": "years and you know that I think actually", "start": 559.85, "duration": 3.57}, {"text": "can end up being much harder than this", "start": 561.95, "duration": 2.61}, {"text": "what I want to talk about next but", "start": 563.42, "duration": 2.88}, {"text": "before we go there have you ever thought", "start": 564.56, "duration": 4.29}, {"text": "about selling the company again since no", "start": 566.3, "duration": 5.49}, {"text": "after that poor name is just yeah got", "start": 568.85, "duration": 4.65}, {"text": "that out of the way we're gonna be here", "start": 571.79, "duration": 5.64}, {"text": "for a long time and yeah cool um yes so", "start": 573.5, "duration": 6.27}, {"text": "I want to talk about one of the most", "start": 577.43, "duration": 3.57}, {"text": "common questions we get from people", "start": 579.77, "duration": 2.88}, {"text": "building products is how to decide what", "start": 581.0, "duration": 3.39}, {"text": "to build how to figure out when to bet", "start": 582.65, "duration": 2.97}, {"text": "the company how to do something totally", "start": 584.39, "duration": 3.39}, {"text": "new yeah and I think one thing that", "start": 585.62, "duration": 3.96}, {"text": "Facebook is done incredibly well is", "start": 587.78, "duration": 4.5}, {"text": "figure out what to build and beep and", "start": 589.58, "duration": 5.31}, {"text": "build this repeated innovation culture", "start": 592.28, "duration": 3.93}, {"text": "which i think is like the hardest thing", "start": 594.89, "duration": 3.87}, {"text": "to do in business so how have you done", "start": 596.21, "duration": 3.96}, {"text": "that and how do you advise other people", "start": 598.76, "duration": 4.88}, {"text": "to do the same I think the key is", "start": 600.17, "duration": 7.65}, {"text": "building a company which is focused on", "start": 603.64, "duration": 5.77}, {"text": "learning as quickly as possible", "start": 607.82, "duration": 3.96}, {"text": "right companies are learning organisms", "start": 609.41, "duration": 6.06}, {"text": "and you can make decisions that either", "start": 611.78, "duration": 5.97}, {"text": "make it's that you learned faster or you", "start": 615.47, "duration": 4.89}, {"text": "learn slower and you know in a lot of", "start": 617.75, "duration": 3.6}, {"text": "ways building a company is like", "start": 620.36, "duration": 3.09}, {"text": "following the scientific method right", "start": 621.35, "duration": 4.35}, {"text": "you try a bunch of different hypotheses", "start": 623.45, "duration": 4.95}, {"text": "and if you set up the experiments well", "start": 625.7, "duration": 5.69}, {"text": "then you kind of learn what to do and", "start": 628.4, "duration": 5.88}, {"text": "that's that's an important philosophy so", "start": 631.39, "duration": 4.33}, {"text": "there are all these different decisions", "start": 634.28, "duration": 3.51}, {"text": "that we make inside the company you know", "start": 635.72, "duration": 4.71}, {"text": "everything down to really empowering", "start": 637.79, "duration": 4.41}, {"text": "individual engineers we invest in this", "start": 640.43, "duration": 4.29}, {"text": "huge testing framework right at any", "start": 642.2, "duration": 4.14}, {"text": "given point in time there aren't there's", "start": 644.72, "duration": 3.15}, {"text": "not just one version of Facebook running", "start": 646.34, "duration": 3.15}, {"text": "in the world right there's probably tens", "start": 647.87, "duration": 3.17}, {"text": "of thousands of versions running because", "start": 649.49, "duration": 5.25}, {"text": "engineers here have the power to to try", "start": 651.04, "duration": 7.42}, {"text": "out idea and and ship it to you know", "start": 654.74, "duration": 5.34}, {"text": "maybe 10,000 people or a hundred", "start": 658.46, "duration": 3.18}, {"text": "thousand people and then they get a", "start": 660.08, "duration": 3.36}, {"text": "readout on how", "start": 661.64, "duration": 3.33}, {"text": "that version of what they did whether it", "start": 663.44, "duration": 4.71}, {"text": "was a change to show better content a", "start": 664.97, "duration": 5.31}, {"text": "newsfeed or UI change or some new", "start": 668.15, "duration": 4.02}, {"text": "feature they could have read out on how", "start": 670.28, "duration": 5.4}, {"text": "that version performed compared to the", "start": 672.17, "duration": 5.34}, {"text": "baseline version of Facebook that we", "start": 675.68, "duration": 3.06}, {"text": "have on everything that we care about", "start": 677.51, "duration": 3.87}, {"text": "how how connected people are you know", "start": 678.74, "duration": 4.11}, {"text": "how much people are sharing and how much", "start": 681.38, "duration": 3.51}, {"text": "they say that they're finding meaningful", "start": 682.85, "duration": 4.59}, {"text": "content business metrics like how much", "start": 684.89, "duration": 4.26}, {"text": "revenue we make and engagement of the", "start": 687.44, "duration": 3.51}, {"text": "overall community and you know by", "start": 689.15, "duration": 3.42}, {"text": "running in tens of thousands of", "start": 690.95, "duration": 3.96}, {"text": "different experiments inputting the", "start": 692.57, "duration": 3.99}, {"text": "power in people's hands to try all these", "start": 694.91, "duration": 3.39}, {"text": "different things you can imagine we just", "start": 696.56, "duration": 3.18}, {"text": "make so much more progress that we could", "start": 698.3, "duration": 2.94}, {"text": "if every change had to be approved by me", "start": 699.74, "duration": 3.36}, {"text": "right already every idea had to come", "start": 701.24, "duration": 4.23}, {"text": "from for management so I do think", "start": 703.1, "duration": 3.36}, {"text": "there's something very deep about", "start": 705.47, "duration": 3.48}, {"text": "building this you know learning culture", "start": 706.46, "duration": 4.62}, {"text": "and moving quickly towards that that", "start": 708.95, "duration": 5.22}, {"text": "just helps you get ahead over time what", "start": 711.08, "duration": 5.1}, {"text": "about the the bigger bets like making a", "start": 714.17, "duration": 3.6}, {"text": "large acquisition or the rollout of a", "start": 716.18, "duration": 2.79}, {"text": "news feed or something like that how do", "start": 717.77, "duration": 3.33}, {"text": "you edit those decisions work so I", "start": 718.97, "duration": 3.36}, {"text": "actually think when you do stuff well", "start": 721.1, "duration": 3.63}, {"text": "you don't you you shouldn't have to do", "start": 722.33, "duration": 6.0}, {"text": "big crazy things right so you want to", "start": 724.73, "duration": 7.86}, {"text": "actually evolve in a way where you're", "start": 728.33, "duration": 5.76}, {"text": "working with your community and making", "start": 732.59, "duration": 3.42}, {"text": "steps and learning so take newsfeed for", "start": 734.09, "duration": 4.83}, {"text": "example that there was a relatively big", "start": 736.01, "duration": 5.4}, {"text": "shift but it actually had been a couple", "start": 738.92, "duration": 4.5}, {"text": "of years in the making by watching what", "start": 741.41, "duration": 3.63}, {"text": "how people were using the service right", "start": 743.42, "duration": 4.05}, {"text": "so know it when we started off we didn't", "start": 745.04, "duration": 4.35}, {"text": "have anything like news feed that showed", "start": 747.47, "duration": 3.84}, {"text": "you updates from from what people were", "start": 749.39, "duration": 4.2}, {"text": "sharing we just had profiles and what we", "start": 751.31, "duration": 4.59}, {"text": "found were originally one of the big", "start": 753.59, "duration": 3.87}, {"text": "behaviors was people just click around", "start": 755.9, "duration": 3.21}, {"text": "right - they'd click on different", "start": 757.46, "duration": 4.08}, {"text": "profiles you know hundreds of them just", "start": 759.11, "duration": 3.6}, {"text": "- and they'd go through all their", "start": 761.54, "duration": 2.76}, {"text": "friends to see what people had changed", "start": 762.71, "duration": 4.04}, {"text": "right to see what the update was and and", "start": 764.3, "duration": 6.06}, {"text": "in in their friends day and we learned", "start": 766.75, "duration": 5.26}, {"text": "from that that people were not just", "start": 770.36, "duration": 3.36}, {"text": "interested in looking up and learning", "start": 772.01, "duration": 3.27}, {"text": "about a person but also understanding", "start": 773.72, "duration": 3.45}, {"text": "the day-to-day changes so you know first", "start": 775.28, "duration": 4.62}, {"text": "we made this product that I just showed", "start": 777.17, "duration": 4.53}, {"text": "in order which of your friends had", "start": 779.9, "duration": 3.42}, {"text": "updated their profile right so that at", "start": 781.7, "duration": 3.0}, {"text": "least told you whose profile to click on", "start": 783.32, "duration": 3.0}, {"text": "and then you know the first version", "start": 784.7, "duration": 3.03}, {"text": "reduced food was really simple all it", "start": 786.32, "duration": 3.3}, {"text": "did was it basically took the content", "start": 787.73, "duration": 3.75}, {"text": "that people were posting and put it in", "start": 789.62, "duration": 6.53}, {"text": "order on on your homepage", "start": 791.48, "duration": 4.67}, {"text": "so I think when you're when when things", "start": 796.16, "duration": 5.73}, {"text": "are working well you use data and you", "start": 798.35, "duration": 5.85}, {"text": "use the qualitative feedback that you're", "start": 801.89, "duration": 4.2}, {"text": "getting from from listening to how your", "start": 804.2, "duration": 4.14}, {"text": "community is using your product to tell", "start": 806.09, "duration": 4.17}, {"text": "you what problems to go solve and then", "start": 808.34, "duration": 4.23}, {"text": "you basically use intuition to figure", "start": 810.26, "duration": 3.66}, {"text": "out what the solutions to those problems", "start": 812.57, "duration": 3.06}, {"text": "might be and then you test those", "start": 813.92, "duration": 3.75}, {"text": "hypotheses by rolling them out and", "start": 815.63, "duration": 3.66}, {"text": "getting more data and feedback on that", "start": 817.67, "duration": 3.12}, {"text": "and then that gives you a sense of where", "start": 819.29, "duration": 3.39}, {"text": "to go um you know when I look at things", "start": 820.79, "duration": 5.28}, {"text": "like you know we bought you know the", "start": 822.68, "duration": 6.18}, {"text": "oculus team for a lot of money right I", "start": 826.07, "duration": 6.6}, {"text": "actually view that as you know if we'd", "start": 828.86, "duration": 6.75}, {"text": "done a better job of building up some of", "start": 832.67, "duration": 4.05}, {"text": "the expertise to do some of that stuff", "start": 835.61, "duration": 3.33}, {"text": "internally then you know maybe we", "start": 836.72, "duration": 3.69}, {"text": "wouldn't have had to do that but you", "start": 838.94, "duration": 3.42}, {"text": "know instead we hadn't done that and you", "start": 840.41, "duration": 3.48}, {"text": "know the oculus team is by far the most", "start": 842.36, "duration": 4.23}, {"text": "talented team working on that problem so", "start": 843.89, "duration": 4.17}, {"text": "it just made sense to go make this big", "start": 846.59, "duration": 3.45}, {"text": "move but I actually kind of think as as", "start": 848.06, "duration": 3.66}, {"text": "CEO it's your job to not get into a", "start": 850.04, "duration": 2.82}, {"text": "position where you need to be doing", "start": 851.72, "duration": 2.94}, {"text": "these crazy things righted yes of course", "start": 852.86, "duration": 3.96}, {"text": "it's inevitable you know over the period", "start": 854.66, "duration": 4.17}, {"text": "of doing stuff you'll you know you can't", "start": 856.82, "duration": 3.44}, {"text": "be ahead of everything so it's better to", "start": 858.83, "duration": 4.14}, {"text": "to make big moves and be willing to do", "start": 860.26, "duration": 5.44}, {"text": "that then you know have pride and and", "start": 862.97, "duration": 4.08}, {"text": "not do that and never admit that you", "start": 865.7, "duration": 3.03}, {"text": "that you could have done something", "start": 867.05, "duration": 3.33}, {"text": "better in the past but but then when", "start": 868.73, "duration": 3.45}, {"text": "stuff is working well you're learning", "start": 870.38, "duration": 3.89}, {"text": "incrementally and and growing that way", "start": 872.18, "duration": 4.59}, {"text": "speaking of growing one thing I heard", "start": 874.27, "duration": 4.45}, {"text": "you say years ago is that one of the", "start": 876.77, "duration": 3.54}, {"text": "best things Facebook had done was invent", "start": 878.72, "duration": 3.99}, {"text": "the idea of a growth group oh and so", "start": 880.31, "duration": 3.66}, {"text": "this is something now that I've heard a", "start": 882.71, "duration": 2.82}, {"text": "lot of founders ask about could you tell", "start": 883.97, "duration": 3.75}, {"text": "us is that still something you recommend", "start": 885.53, "duration": 3.96}, {"text": "people running companies put in place", "start": 887.72, "duration": 3.51}, {"text": "and how Facebook's worked in the early", "start": 889.49, "duration": 4.29}, {"text": "days so making it so we could grow", "start": 891.23, "duration": 6.24}, {"text": "faster was I think the most important", "start": 893.78, "duration": 5.61}, {"text": "product feature that we ended up", "start": 897.47, "duration": 3.99}, {"text": "building for Facebook and you know the", "start": 899.39, "duration": 3.66}, {"text": "traditional approach to growing and", "start": 901.46, "duration": 4.02}, {"text": "marketing is you know you have a", "start": 903.05, "duration": 3.78}, {"text": "communications group or you have a", "start": 905.48, "duration": 3.15}, {"text": "marketing team and you buy ads and yeah", "start": 906.83, "duration": 3.36}, {"text": "you know I think there's some sometimes", "start": 908.63, "duration": 2.79}, {"text": "there's a place for it for that", "start": 910.19, "duration": 2.64}, {"text": "especially when you're trying to", "start": 911.42, "duration": 3.06}, {"text": "communicate something and get a message", "start": 912.83, "duration": 5.28}, {"text": "out but if you're actually trying to to", "start": 914.48, "duration": 6.45}, {"text": "grow a product I think the often the", "start": 918.11, "duration": 3.99}, {"text": "best levers for doing that are within", "start": 920.93, "duration": 2.7}, {"text": "the product themselves and getting", "start": 922.1, "duration": 3.18}, {"text": "people in your community who enjoy what", "start": 923.63, "duration": 4.35}, {"text": "you're doing to evangelize that to their", "start": 925.28, "duration": 3.72}, {"text": "friends and getting that to happen", "start": 927.98, "duration": 2.1}, {"text": "efficiently as if", "start": 929.0, "duration": 3.87}, {"text": "as possible so there's no magic in the", "start": 930.08, "duration": 5.01}, {"text": "growth group that we that we built that", "start": 932.87, "duration": 3.81}, {"text": "other people can't replicate you know", "start": 935.09, "duration": 3.27}, {"text": "it's it's just being very rigorous with", "start": 936.68, "duration": 3.87}, {"text": "data investing in data infrastructure so", "start": 938.36, "duration": 4.05}, {"text": "that way you can process all these", "start": 940.55, "duration": 3.45}, {"text": "different experiments and learn what", "start": 942.41, "duration": 3.84}, {"text": "people are trying to tell you and and", "start": 944.0, "duration": 4.32}, {"text": "then go invest engineering and actually", "start": 946.25, "duration": 3.75}, {"text": "trying to grow the community cuz I think", "start": 948.32, "duration": 3.09}, {"text": "that's the most important feature for a", "start": 950.0, "duration": 3.18}, {"text": "lot of networks and can you tell how", "start": 951.41, "duration": 3.75}, {"text": "much of an impact that group had on the", "start": 953.18, "duration": 5.4}, {"text": "growth rate of Facebook um yeah I think", "start": 955.16, "duration": 7.38}, {"text": "it's you know their overall I think it's", "start": 958.58, "duration": 7.44}, {"text": "been very big I don't have a number off", "start": 962.54, "duration": 4.95}, {"text": "the top my head but I've been even just", "start": 966.02, "duration": 4.37}, {"text": "looking at your just some of these", "start": 967.49, "duration": 5.52}, {"text": "specific features that we've built like", "start": 970.39, "duration": 4.66}, {"text": "people you may know right which is yeah", "start": 973.01, "duration": 4.44}, {"text": "you know one of the important things", "start": 975.05, "duration": 4.05}, {"text": "right again if you're you know social", "start": 977.45, "duration": 2.88}, {"text": "product isn't that useful if you're not", "start": 979.1, "duration": 3.18}, {"text": "connected to other people you want in", "start": 980.33, "duration": 5.1}, {"text": "your using it so you know helping you go", "start": 982.28, "duration": 5.43}, {"text": "from signing up for Facebook to", "start": 985.43, "duration": 3.42}, {"text": "connecting to the people that you care", "start": 987.71, "duration": 2.94}, {"text": "about most is probably one of the most", "start": 988.85, "duration": 4.08}, {"text": "important things that we can do another", "start": 990.65, "duration": 3.42}, {"text": "thing that I think Facebook is done", "start": 992.93, "duration": 3.57}, {"text": "exceptionally well is hiring and and I", "start": 994.07, "duration": 3.63}, {"text": "always tell founders that this is the", "start": 996.5, "duration": 3.51}, {"text": "thing you have to get good at so how", "start": 997.7, "duration": 5.04}, {"text": "have you hired your team and what do you", "start": 1000.01, "duration": 4.65}, {"text": "look for when you bring people on if you", "start": 1002.74, "duration": 3.78}, {"text": "think about it you know I started the", "start": 1004.66, "duration": 4.94}, {"text": "company one has 19 right so I can't", "start": 1006.52, "duration": 5.16}, {"text": "institutionally believe that experience", "start": 1009.6, "duration": 3.55}, {"text": "is that important right or else I would", "start": 1011.68, "duration": 3.93}, {"text": "have a hard time reconciling to myself", "start": 1013.15, "duration": 5.37}, {"text": "right and and and the company so you", "start": 1015.61, "duration": 6.12}, {"text": "know we invest in in people who we think", "start": 1018.52, "duration": 5.31}, {"text": "are just really talented even if they", "start": 1021.73, "duration": 4.26}, {"text": "haven't done that thing before and you", "start": 1023.83, "duration": 3.96}, {"text": "know that applies to people who are", "start": 1025.99, "duration": 5.16}, {"text": "fresh out of university as well as you", "start": 1027.79, "duration": 5.52}, {"text": "know people like you know the CFO who", "start": 1031.15, "duration": 3.72}, {"text": "took the company public and not taking a", "start": 1033.31, "duration": 2.94}, {"text": "company public before right and hit a", "start": 1034.87, "duration": 3.42}, {"text": "lot of his background was in you know", "start": 1036.25, "duration": 4.35}, {"text": "production development to Genentech", "start": 1038.29, "duration": 4.62}, {"text": "before so you know just focus on really", "start": 1040.6, "duration": 4.02}, {"text": "talented people and so if you don't have", "start": 1042.91, "duration": 3.39}, {"text": "the experience to look for how do you", "start": 1044.62, "duration": 4.1}, {"text": "assess someone's raw talent um", "start": 1046.3, "duration": 5.67}, {"text": "well often you can tell from different", "start": 1048.72, "duration": 4.81}, {"text": "things that they've done right so it's", "start": 1051.97, "duration": 3.09}, {"text": "it's not that you know obviously", "start": 1053.53, "duration": 3.18}, {"text": "everyone's done something right if even", "start": 1055.06, "duration": 3.78}, {"text": "if you're 19 right you've um you've done", "start": 1056.71, "duration": 5.81}, {"text": "side projects and interesting stuff", "start": 1058.84, "duration": 6.05}, {"text": "and you know I think what's important is", "start": 1062.52, "duration": 4.11}, {"text": "not to believe that someone has to have", "start": 1064.89, "duration": 3.66}, {"text": "specifically done the job that they're", "start": 1066.63, "duration": 3.96}, {"text": "going to do in order to be able to to do", "start": 1068.55, "duration": 3.81}, {"text": "it well one of the things that I think", "start": 1070.59, "duration": 4.589}, {"text": "we've done well is is just given the", "start": 1072.36, "duration": 3.87}, {"text": "people at the company a lot of", "start": 1075.179, "duration": 2.911}, {"text": "opportunity right so you know it's not", "start": 1076.23, "duration": 3.6}, {"text": "just me who started when I was 19 and", "start": 1078.09, "duration": 3.6}, {"text": "and now you know I'm running this big", "start": 1079.83, "duration": 3.27}, {"text": "company there were a number of people", "start": 1081.69, "duration": 3.72}, {"text": "who joined who were you know people I", "start": 1083.1, "duration": 4.41}, {"text": "did problem sets with at Harvard or they", "start": 1085.41, "duration": 3.99}, {"text": "dropped out of Stanford or you know", "start": 1087.51, "duration": 3.57}, {"text": "different programs who have grown with", "start": 1089.4, "duration": 2.909}, {"text": "the company over this long period of", "start": 1091.08, "duration": 2.7}, {"text": "time and you know one of the things that", "start": 1092.309, "duration": 4.111}, {"text": "I'm the most proud of is we have about", "start": 1093.78, "duration": 4.02}, {"text": "12 different product groups of the", "start": 1096.42, "duration": 4.59}, {"text": "company and all of the people who are", "start": 1097.8, "duration": 8.0}, {"text": "running them with the exception of one I", "start": 1101.01, "duration": 7.11}, {"text": "did not join the company running a", "start": 1105.8, "duration": 3.97}, {"text": "product group or reporting to me that's", "start": 1108.12, "duration": 4.14}, {"text": "amazing um and the one exception was is", "start": 1109.77, "duration": 5.94}, {"text": "David Marcus who was the CEO of a fifty", "start": 1112.26, "duration": 5.669}, {"text": "billion dollar public company so you", "start": 1115.71, "duration": 4.23}, {"text": "know some pretty happy that that he's on", "start": 1117.929, "duration": 3.571}, {"text": "board and having him run a product group", "start": 1119.94, "duration": 3.239}, {"text": "I think is a pretty big coup too but", "start": 1121.5, "duration": 2.85}, {"text": "literally none of them started off", "start": 1123.179, "duration": 1.981}, {"text": "reporting to me", "start": 1124.35, "duration": 2.25}, {"text": "you know they all start off in different", "start": 1125.16, "duration": 2.94}, {"text": "different roles some where engineers", "start": 1126.6, "duration": 3.66}, {"text": "some where data analysts some where", "start": 1128.1, "duration": 3.9}, {"text": "product managers and they've all grown", "start": 1130.26, "duration": 4.02}, {"text": "but I think what happens is you know", "start": 1132.0, "duration": 3.27}, {"text": "people see that you create opportunities", "start": 1134.28, "duration": 3.779}, {"text": "for people and and that also I think", "start": 1135.27, "duration": 4.95}, {"text": "keeps the best people engaged and makes", "start": 1138.059, "duration": 3.241}, {"text": "the best people want to come work at", "start": 1140.22, "duration": 2.01}, {"text": "your company because they feel like oh", "start": 1141.3, "duration": 1.68}, {"text": "I'm going to get those kind of", "start": 1142.23, "duration": 3.93}, {"text": "opportunities - cool yeah what are you", "start": 1142.98, "duration": 5.31}, {"text": "most excited about over the next 20", "start": 1146.16, "duration": 3.0}, {"text": "years what do you think will be the", "start": 1148.29, "duration": 2.43}, {"text": "major transformations how will Facebook", "start": 1149.16, "duration": 3.18}, {"text": "transform how do you think the rest of", "start": 1150.72, "duration": 4.709}, {"text": "the world to transform so we have this", "start": 1152.34, "duration": 5.04}, {"text": "ten-year roadmap I was great you know", "start": 1155.429, "duration": 4.5}, {"text": "three of the the big changes that we", "start": 1157.38, "duration": 4.5}, {"text": "want to see in the world and we're", "start": 1159.929, "duration": 3.151}, {"text": "focused on three things", "start": 1161.88, "duration": 3.21}, {"text": "connectivity rights are getting everyone", "start": 1163.08, "duration": 3.0}, {"text": "in the world on the Internet", "start": 1165.09, "duration": 2.61}, {"text": "right now more than you know more than", "start": 1166.08, "duration": 3.0}, {"text": "half the world is not on the Internet", "start": 1167.7, "duration": 3.18}, {"text": "which is you know I think a lot of", "start": 1169.08, "duration": 4.02}, {"text": "people in Silicon Valley quite take this", "start": 1170.88, "duration": 4.41}, {"text": "for granted right the internet because", "start": 1173.1, "duration": 3.78}, {"text": "it you know it's it just is not", "start": 1175.29, "duration": 3.21}, {"text": "uniformly available and if we want to", "start": 1176.88, "duration": 4.92}, {"text": "solve a lot of the the big challenges of", "start": 1178.5, "duration": 5.07}, {"text": "the world today they're not problems", "start": 1181.8, "duration": 3.36}, {"text": "that any one group of people or even one", "start": 1183.57, "duration": 3.54}, {"text": "country can solve right they they really", "start": 1185.16, "duration": 3.63}, {"text": "involve coming together and giving", "start": 1187.11, "duration": 3.03}, {"text": "everyone an opportunity to participate", "start": 1188.79, "duration": 3.96}, {"text": "and solving them so I think connecting", "start": 1190.14, "duration": 4.3}, {"text": "everyone is is really a key", "start": 1192.75, "duration": 5.11}, {"text": "which is going to be be great for for", "start": 1194.44, "duration": 7.1}, {"text": "people around the world the next one is", "start": 1197.86, "duration": 7.8}, {"text": "AI I think that that's just gonna unlock", "start": 1201.54, "duration": 6.37}, {"text": "so much potential in so many different", "start": 1205.66, "duration": 5.1}, {"text": "domains and we use it at Facebook for a", "start": 1207.91, "duration": 4.11}, {"text": "lot of different things for showing", "start": 1210.76, "duration": 2.25}, {"text": "people content that they're going to", "start": 1212.02, "duration": 3.06}, {"text": "find more meaningful for making sure", "start": 1213.01, "duration": 4.02}, {"text": "that you connect with the people you", "start": 1215.08, "duration": 4.02}, {"text": "actually care about on the service but", "start": 1217.03, "duration": 4.74}, {"text": "in a lot of ways the work that we're", "start": 1219.1, "duration": 7.38}, {"text": "doing on AI to push the fundamental you", "start": 1221.77, "duration": 6.69}, {"text": "know state of the art forward is exactly", "start": 1226.48, "duration": 3.6}, {"text": "the same stuff that's going into systems", "start": 1228.46, "duration": 3.36}, {"text": "that diagnose diseases better right or", "start": 1230.08, "duration": 4.1}, {"text": "find better drugs to treat people or", "start": 1231.82, "duration": 5.07}, {"text": "that you know other companies are using", "start": 1234.18, "duration": 5.44}, {"text": "when they build self-driving cars and", "start": 1236.89, "duration": 3.78}, {"text": "you know these are things they're going", "start": 1239.62, "duration": 2.52}, {"text": "to save lives right I mean if you can I", "start": 1240.67, "duration": 4.2}, {"text": "heard this story recently that at this", "start": 1242.14, "duration": 6.68}, {"text": "conference where someone has built a", "start": 1244.87, "duration": 6.06}, {"text": "machine learning application where you", "start": 1248.82, "duration": 4.87}, {"text": "can take a picture of a lesion on", "start": 1250.93, "duration": 4.89}, {"text": "someone's skin and it can detect", "start": 1253.69, "duration": 5.34}, {"text": "instantly whether it's skin cancer with", "start": 1255.82, "duration": 6.21}, {"text": "the accuracy of the best dermatologists", "start": 1259.03, "duration": 4.98}, {"text": "and doctors in the world so you know I", "start": 1262.03, "duration": 3.24}, {"text": "mean who doesn't want that right now", "start": 1264.01, "duration": 2.67}, {"text": "like you're gonna build to put the power", "start": 1265.27, "duration": 4.35}, {"text": "in your doctors hand to become the best", "start": 1266.68, "duration": 4.2}, {"text": "doctor of the world at that thing", "start": 1269.62, "duration": 2.58}, {"text": "everyone will be the best doctor in the", "start": 1270.88, "duration": 3.72}, {"text": "world and that's a really fundamental", "start": 1272.2, "duration": 6.39}, {"text": "thing right that you know I I get a", "start": 1274.6, "duration": 5.25}, {"text": "little bit frustrated I think when", "start": 1278.59, "duration": 4.05}, {"text": "people you know fearmonger about about", "start": 1279.85, "duration": 4.77}, {"text": "AI and how it could end up hurting", "start": 1282.64, "duration": 4.26}, {"text": "people because I think in many real ways", "start": 1284.62, "duration": 3.72}, {"text": "around diseases or not driving more", "start": 1286.9, "duration": 3.18}, {"text": "safely this is going to save people's", "start": 1288.34, "duration": 3.42}, {"text": "lives and push and push people for it so", "start": 1290.08, "duration": 3.48}, {"text": "that that's a really big deal I think", "start": 1291.76, "duration": 3.99}, {"text": "for the next ten years and then you know", "start": 1293.56, "duration": 4.56}, {"text": "the next thing that I always think is is", "start": 1295.75, "duration": 5.19}, {"text": "going to make a big difference is um you", "start": 1298.12, "duration": 4.32}, {"text": "know over 10 or 15 years there's a new", "start": 1300.94, "duration": 3.27}, {"text": "major computing platform that comes", "start": 1302.44, "duration": 3.84}, {"text": "around that allows people to do", "start": 1304.21, "duration": 3.18}, {"text": "completely different things than they", "start": 1306.28, "duration": 3.15}, {"text": "could do before right so you know 20", "start": 1307.39, "duration": 3.87}, {"text": "years ago you know most of us were using", "start": 1309.43, "duration": 3.96}, {"text": "desktop computers they were kind of", "start": 1311.26, "duration": 3.96}, {"text": "clunky you know we use them and work", "start": 1313.39, "duration": 4.29}, {"text": "because commit our work more productive", "start": 1315.22, "duration": 4.08}, {"text": "but most people didn't use them for fun", "start": 1317.68, "duration": 4.02}, {"text": "now we have phones which you know help", "start": 1319.3, "duration": 3.66}, {"text": "us connect with each other and they're", "start": 1321.7, "duration": 3.12}, {"text": "much more human devices but there's", "start": 1322.96, "duration": 3.75}, {"text": "going to be another platform after that", "start": 1324.82, "duration": 4.32}, {"text": "and I think that's going to be virtual", "start": 1326.71, "duration": 5.61}, {"text": "reality and augmented reality and that I", "start": 1329.14, "duration": 4.98}, {"text": "think is just going to help people you", "start": 1332.32, "duration": 4.83}, {"text": "know be more creative experience what", "start": 1334.12, "duration": 4.89}, {"text": "other people are feeling much more", "start": 1337.15, "duration": 3.9}, {"text": "immersively than we even can through", "start": 1339.01, "duration": 3.9}, {"text": "through video and things like that today", "start": 1341.05, "duration": 4.23}, {"text": "so I'm really excited about that trend", "start": 1342.91, "duration": 4.59}, {"text": "as well so you were nineteen when you", "start": 1345.28, "duration": 4.56}, {"text": "started Facebook one question we hear a", "start": 1347.5, "duration": 4.62}, {"text": "lot that Y Combinator is I'm 19 today I", "start": 1349.84, "duration": 4.14}, {"text": "really want to you know do whatever I", "start": 1352.12, "duration": 3.39}, {"text": "can to make the world better what should", "start": 1353.98, "duration": 1.92}, {"text": "I do", "start": 1355.51, "duration": 2.67}, {"text": "so how do you advise people who are 90", "start": 1355.9, "duration": 4.53}, {"text": "today and want to impact the world like", "start": 1358.18, "duration": 4.23}, {"text": "you have you know I always think that", "start": 1360.43, "duration": 2.82}, {"text": "the most important thing that", "start": 1362.41, "duration": 2.58}, {"text": "entrepreneurs should do is pick", "start": 1363.25, "duration": 3.93}, {"text": "something they care about work on it but", "start": 1364.99, "duration": 3.72}, {"text": "don't actually commit to turning it into", "start": 1367.18, "duration": 3.6}, {"text": "a company until it's working and I think", "start": 1368.71, "duration": 3.78}, {"text": "that if you look at the data of like the", "start": 1370.78, "duration": 2.82}, {"text": "very best companies that have gotten", "start": 1372.49, "duration": 2.7}, {"text": "built I actually think a tremendous", "start": 1373.6, "duration": 3.6}, {"text": "percent of them have been built that way", "start": 1375.19, "duration": 4.02}, {"text": "and not from people who decided upfront", "start": 1377.2, "duration": 2.88}, {"text": "that they wanted to start a company", "start": 1379.21, "duration": 2.28}, {"text": "because you just get locked into some", "start": 1380.08, "duration": 3.15}, {"text": "local minimum a lot of the time a local", "start": 1381.49, "duration": 3.84}, {"text": "maximum I totally agree and just to make", "start": 1383.23, "duration": 3.99}, {"text": "this point how far into Facebook did it", "start": 1385.33, "duration": 7.29}, {"text": "actually become a company um I don't", "start": 1387.22, "duration": 6.09}, {"text": "know", "start": 1392.62, "duration": 3.62}, {"text": "I think probably I think it became a a", "start": 1393.31, "duration": 6.06}, {"text": "formal Delaware company when Peter Thiel", "start": 1396.24, "duration": 6.76}, {"text": "invested about six months in when we", "start": 1399.37, "duration": 4.74}, {"text": "were first talking to Peter about", "start": 1403.0, "duration": 3.09}, {"text": "raising money Dustin and I were very", "start": 1404.11, "duration": 3.54}, {"text": "clear with him that we were planning on", "start": 1406.09, "duration": 4.53}, {"text": "going back to school ready Nara you know", "start": 1407.65, "duration": 5.7}, {"text": "I started Facebook own as a sophomore we", "start": 1410.62, "duration": 4.71}, {"text": "took the summer offered no classes over", "start": 1413.35, "duration": 3.3}, {"text": "the summer we were working on it and", "start": 1415.33, "duration": 3.9}, {"text": "then you know our stated game plan was", "start": 1416.65, "duration": 4.05}, {"text": "to go back to school in the fall and", "start": 1419.23, "duration": 3.72}, {"text": "continue working on it then but not like", "start": 1420.7, "duration": 4.14}, {"text": "sit sit in an office and work on it", "start": 1422.95, "duration": 3.45}, {"text": "full-time and Peter was just kind of", "start": 1424.84, "duration": 3.36}, {"text": "like alright sure you are I guess he", "start": 1426.4, "duration": 2.91}, {"text": "knew better than we think he just", "start": 1428.2, "duration": 2.19}, {"text": "believed that you weren't actually gonna", "start": 1429.31, "duration": 2.46}, {"text": "go back to high you must have I mean", "start": 1430.39, "duration": 3.06}, {"text": "you'd have to ask him but I will were", "start": 1431.77, "duration": 2.85}, {"text": "interviewing him in this series I was", "start": 1433.45, "duration": 3.36}, {"text": "very good so I I think he would probably", "start": 1434.62, "duration": 3.75}, {"text": "say that he knew that we were not going", "start": 1436.81, "duration": 3.09}, {"text": "to go back to school or believed that he", "start": 1438.37, "duration": 3.24}, {"text": "could talk us out of it but he didn't", "start": 1439.9, "duration": 2.94}, {"text": "have to it was it was pretty clear that", "start": 1441.61, "duration": 3.69}, {"text": "the amount of work was just growing so", "start": 1442.84, "duration": 5.1}, {"text": "quickly but we actually did drop out", "start": 1445.3, "duration": 3.12}, {"text": "immediately", "start": 1447.94, "duration": 2.04}, {"text": "we told Harvard that we were taking one", "start": 1448.42, "duration": 4.05}, {"text": "semester off and and then we told her", "start": 1449.98, "duration": 4.08}, {"text": "that we take another semester off and", "start": 1452.47, "duration": 3.87}, {"text": "then a year off and then after that we", "start": 1454.06, "duration": 2.71}, {"text": "kind of", "start": 1456.34, "duration": 2.83}, {"text": "we were going back uh speaking of Peter", "start": 1456.77, "duration": 4.08}, {"text": "and a sort of a closing question what's", "start": 1459.17, "duration": 3.0}, {"text": "the best piece of advice he ever gave", "start": 1460.85, "duration": 7.29}, {"text": "you I think Peter was the person who who", "start": 1462.17, "duration": 9.9}, {"text": "told me this really pithy quote that in", "start": 1468.14, "duration": 7.83}, {"text": "a world that's changing so quickly the", "start": 1472.07, "duration": 7.26}, {"text": "biggest risk you can take is not taking", "start": 1475.97, "duration": 6.51}, {"text": "any risk and I really think that that's", "start": 1479.33, "duration": 5.16}, {"text": "true right a lot of people I think think", "start": 1482.48, "duration": 4.89}, {"text": "that you know whenever it comes to", "start": 1484.49, "duration": 4.5}, {"text": "whatever you get yourself into a", "start": 1487.37, "duration": 3.36}, {"text": "position where you have to make some", "start": 1488.99, "duration": 3.63}, {"text": "some big shift in direction or do", "start": 1490.73, "duration": 5.16}, {"text": "something you know they're always people", "start": 1492.62, "duration": 5.37}, {"text": "are going to point to the downside risks", "start": 1495.89, "duration": 6.03}, {"text": "of that decision and locally there may", "start": 1497.99, "duration": 6.15}, {"text": "be right right I mean if for any given", "start": 1501.92, "duration": 2.97}, {"text": "decision that you're going to make", "start": 1504.14, "duration": 3.09}, {"text": "there's upside and downside but in", "start": 1504.89, "duration": 5.07}, {"text": "aggregate if you are stagnant and you", "start": 1507.23, "duration": 5.76}, {"text": "don't make those changes then then I", "start": 1509.96, "duration": 4.349}, {"text": "think you're guaranteed to fail right", "start": 1512.99, "duration": 3.99}, {"text": "and not not catch up so to some degree I", "start": 1514.309, "duration": 5.011}, {"text": "think it's really right that over time", "start": 1516.98, "duration": 4.68}, {"text": "the biggest risk that you can take is to", "start": 1519.32, "duration": 4.47}, {"text": "not take any risks that is a great place", "start": 1521.66, "duration": 3.66}, {"text": "to leave it thank you very much all", "start": 1523.79, "duration": 3.62}, {"text": "right", "start": 1525.32, "duration": 2.09}]